mcts/__init__.py
mcts/tree_node.py
mcts/utils.py
nim/__init__.py
nim/environment.py
nim/players.py
nim/utils.py
players/__init__.py
players/context.py
players/human_player.py
players/mcts_player.py
utils/__init__.py
utils/play.py
mcts_kds-0.0.0.dist-info/METADATA
mcts_kds-0.0.0.dist-info/WHEEL
mcts_kds-0.0.0.dist-info/top_level.txt
mcts_kds-0.0.0.dist-info/RECORD
