Metadata-Version: 2.1
Name: mcts-kds
Version: 0.0.0
Summary: MCTS Library
Home-page: UNKNOWN
Author: KDS
Author-email: UNKNOWN
License: UNKNOWN
Platform: UNKNOWN
